<resources>
	<resource priority="1" restart="0" delayed="0" disableForEvent="1">analytics</resource>
  <resource priority="1" restart="0" delayed="0" disableForEvent="0">controller</resource>
	<resource priority="1" restart="1" delayed="0" disableForEvent="0">gc</resource>
	<resource priority="1" restart="0" delayed="0" disableForEvent="0">mrgreen-vip</resource>
	<resource priority="1" restart="0" delayed="0" disableForEvent="0">scoreboard</resource>
	<resource priority="1" restart="0" delayed="0" disableForEvent="0">mapmanager</resource>
	<resource priority="1" restart="0" delayed="0" disableForEvent="0">votemanager</resource>
	<resource priority="1" restart="0" delayed="0" disableForEvent="0">resourcebrowser</resource>
	<resource priority="1" restart="0" delayed="0" disableForEvent="0">resourcemanager</resource>
	<resource priority="1" restart="0" delayed="0" disableForEvent="0">joinquit</resource>
	<resource priority="1" restart="0" delayed="0" disableForEvent="0">messages</resource>
	<resource priority="1" restart="0" delayed="0" disableForEvent="0">anti</resource>
	<resource priority="1" restart="0" delayed="0" disableForEvent="0">race</resource>
	<resource priority="1" restart="1" delayed="0" disableForEvent="0">gcshop</resource>
	<resource priority="0" restart="0" delayed="0" disableForEvent="0">maptools</resource>
	<resource priority="1" restart="0" delayed="0" disableForEvent="0">admin</resource>
	<resource priority="1" restart="0" delayed="0" disableForEvent="0">nickprotection</resource>
	<resource priority="1" restart="0" delayed="0" disableForEvent="0">gus</resource>
	<resource priority="0" restart="0" delayed="0" disableForEvent="0">geoloc</resource>
	<resource priority="0" restart="0" delayed="0" disableForEvent="0">fps</resource>
	<resource priority="0" restart="0" delayed="0" disableForEvent="0">voice</resource>
	<resource priority="1" restart="0" delayed="0" disableForEvent="0">webadmin</resource>
	<resource priority="1" restart="0" delayed="0" disableForEvent="0">webpanel</resource>
	<resource priority="0" restart="0" delayed="0" disableForEvent="1">interchat</resource>
	<resource priority="0" restart="0" delayed="0" disableForEvent="0">speed-o-meter</resource>
	<resource priority="0" restart="0" delayed="0" disableForEvent="0">chatbox_ads</resource>
	<resource priority="0" restart="0" delayed="0" disableForEvent="0">PrivateMessaging</resource>
	<resource priority="0" restart="0" delayed="0" disableForEvent="0">radio</resource>
	<resource priority="0" restart="0" delayed="0" disableForEvent="0">runcode</resource>
	<resource priority="0" restart="0" delayed="0" disableForEvent="0">mapratings</resource>
  <resource priority="0" restart="0" delayed="0" disableForEvent="0">map_window</resource>
	<resource priority="0" restart="0" delayed="0" disableForEvent="0">helpmenu</resource>
	<resource priority="1" restart="0" delayed="0" disableForEvent="0">mrgreen-sidebar</resource>
	<resource priority="1" restart="0" delayed="0" disableForEvent="0">mrgreen-settings</resource>
	<resource priority="1" restart="0" delayed="0" disableForEvent="1">mrgreen-stats</resource>
	<resource priority="0" restart="0" delayed="0" disableForEvent="0">irc</resource>
	<resource priority="0" restart="0" delayed="0" disableForEvent="0">achievements</resource>
	<resource priority="0" restart="0" delayed="0" disableForEvent="0">discord</resource>
	<resource priority="1" restart="0" delayed="0" disableForEvent="0">chattags</resource>
	<resource priority="0" restart="0" delayed="0" disableForEvent="0">playerrecord</resource>
	<resource priority="0" restart="0" delayed="0" disableForEvent="0">hdwheels</resource>
	<resource priority="0" restart="0" delayed="0" disableForEvent="0">gctransfer</resource>
	<resource priority="0" restart="0" delayed="0" disableForEvent="0">eventmanager</resource>
	<resource priority="0" restart="1" delayed="0" disableForEvent="0">race_ghost_assist</resource>
	<resource priority="0" restart="0" delayed="0" disableForEvent="0">laps</resource>
	<resource priority="0" restart="0" delayed="0" disableForEvent="0">auto-shutdown</resource>
	<resource priority="0" restart="0" delayed="0" disableForEvent="0">discord_rich_presence</resource>
	<resource priority="0" restart="0" delayed="0" disableForEvent="0">race_progress_3d</resource>
	<resource priority="0" restart="0" delayed="1" disableForEvent="1">ipb</resource>
</resources>
